{"inkVersion":21,"root":[["^TOADSHOE>>Welcome, new detective!","\n","^We're excited to have you here at the Forest Regional Organization of Gumshoes!","\n","^But since we're known for our reliability, naturally we must ask...","\n","^Are you up for the job?","\n","^YOU>>Yes, of course!","\n","^It's been my dream ever since I was a tadpole to—","\n","^TOADSHOE>>Great! Then you should have no problem following my instructions!","\n","^So I actually have something for you in the storage closet.","\n","^Do you think you could grab that?","\n","^YOU>>Sure!","\n","^>>. . .","\n","^YOU>>Uhh, where <i>is</i> the storage closet?","\n","^TOADSHOE>>Oh, it's past this brown door over here.","\n","^Only issue is...I'm not quite sure where I put my keys.","\n","^YOU>>...","\n","^TOADSHOE>>I'm pretty sure I left them in this room though.","\n","^Think you could find them for me?","\n","^YOU>>Uh, yeah! Sure!","\n","ev","str","^0","/str","/ev",{"*":"0.c-0","flg":4},{"c-0":["^ ",{"->":"remember"},"\n",{"->":"0.g-0"},{"#f":5}],"g-0":["done",{"#f":5}]}],"done",{"remember":[["^YOU>>Hmm... Not here either, huh?","\n","^TOADSHOE>>Oh, I just remembered!","\n","^They're still in my coat pocket!","\n","^My coat's right there, on that rack.","\n","ev","str","^0","/str","/ev",{"*":".^.c-0","flg":4},{"c-0":["^ ",{"->":"keys"},"\n",{"#f":5}]}],{"#f":1}],"keys":[["^YOU>>Is it this one?","\n","^TOADSHOE>>Yep! You should be good to unlock the door now.","\n","ev","str","^0","/str","/ev",{"*":".^.c-0","flg":4},{"c-0":["^ ",{"->":"storage"},"\n",{"#f":5}]}],{"#f":1}],"storage":[["^YOU>>This is the storage room?","\n","^It's even bigger than your office...","\n","^TOADSHOE>>Oh, no, it's not in my storage room.","\n","^It's in my storage <i>storage</i> room, actually.","\n","^You'll have to get it open.","\n","ev","str","^0","/str","/ev",{"*":".^.c-0","flg":4},{"c-0":["^ ",{"->":"storage_door"},"\n",{"#f":5}]}],{"#f":1}],"storage_door":[["^YOU>>Whew! That was a workout!","\n","^You said it's this next room?","\n","^TOADSHOE>>Yep! It's right over here...","\n","ev","str","^0","/str","/ev",{"*":".^.c-0","flg":4},{"c-0":["^ ",{"->":"storage_storage"},"\n",{"#f":5}]}],{"#f":1}],"storage_storage":[["^TOADSHOE>>Here we are! My storage storage room!","\n","^YOU>>Great! So where's the thing?","\n","^TOADSHOE>>Oh, it's just up on the top shelf over there.","\n","^YOU>>...Oh.","\n","ev","str","^0","/str","/ev",{"*":".^.c-0","flg":4},{"c-0":["^ ",{"->":"retrieved"},"\n",{"#f":5}]}],{"#f":1}],"retrieved":["^YOU>>What is this?","\n","^\"Lilypad Landing\"...?","\n","^TOADSHOE>>It's your job posting, of course!","\n","^That's where you're going to be stationed!","\n","^YOU>>But isn't Lilypad Landing the town with a 0% crime rate?","\n","^TOADSHOE>>Well, apparently a mysterious death recently occurred there, and we aren't quite sure what the situation is.","\n","^So who better than you to look into it?","\n","^YOU>>A <i>murder</i>...?","\n","^TOADSHOE>>There is no proof that this is a case of murder.","\n","^But who knows, maybe you'll find something that we couldn't?","\n","^YOU>>Hmmmm, <i>okay......</i>","\n","^TOADSHOE>>And remember: why do we do our work here at FROG?","\n","^YOU>>For the safety of the Forest!","\n","^TOADSHOE>>That's right!","\n","^Now hurry along. You have a job to do, after all.","\n","end",{"#f":1}],"#f":1}],"listDefs":{}}